{
  "infoStoreOptions": {
    "transformMap": {
      "type": "name",
      "version": "version",
      "hardware": "hardware",
      "description": "description",
      "fileSize": "fileSize",
      "md5": "fileMd5",
      "date": "releasedAt",
      "fileName": "mainFileName"
    }
  },
  "inputMoveOptions": {
    "items": [
      { "source": "README.md", "target": "RRRRRRRRRRRRRRRRRRRRRRRRRR.md" },
      {
        "source": "lib/plugins",
        "target": "llllllllllllllllllllllllllllllll"
      }
    ]
  }
}
